[
  {
    "domain": ".facebook.com",
    "expirationDate": 1774006018.0,
    "hostOnly": false,
    "httpOnly": false,
    "name": "c_user",
    "path": "/",
    "sameSite": "no_restriction",
    "secure": true,
    "session": false,
    "storeId": null,
    "value": "61572830469986"
  },
  {
    "domain": ".facebook.com",
    "expirationDate": null,
    "hostOnly": false,
    "httpOnly": false,
    "name": "presence",
    "path": "/",
    "sameSite": "no_restriction",
    "secure": true,
    "session": true,
    "storeId": null,
    "value": "C%7B%22t3%22%3A%5B%5D%2C%22utc3%22%3A1742444818001%2C%22v%22%3A1%7D"
  },
  {
    "domain": "www.facebook.com",
    "expirationDate": null,
    "hostOnly": false,
    "httpOnly": false,
    "name": "xs",
    "path": "/",
    "sameSite": "no_restriction",
    "secure": true,
    "session": true,
    "storeId": null,
    "value": "50%3AUe0eL0TgvDGnKg%3A2%3A1739086045%3A-1%3A10542%3A%3AAcUQeUdh2toMkMk-IS_p4BSUX4ClkVDDBOIsuD3fIv4"
  },
  {
    "domain": "www.facebook.com",
    "expirationDate": null,
    "hostOnly": false,
    "httpOnly": false,
    "name": "presence",
    "path": "/",
    "sameSite": "no_restriction",
    "secure": true,
    "session": true,
    "storeId": null,
    "value": "C%7B%22t3%22%3A%5B%5D%2C%22utc3%22%3A1742443647420%2C%22v%22%3A1%7D"
  },
  {
    "domain": "www.facebook.com",
    "expirationDate": null,
    "hostOnly": false,
    "httpOnly": false,
    "name": "fr",
    "path": "/",
    "sameSite": "no_restriction",
    "secure": true,
    "session": true,
    "storeId": null,
    "value": "1cr2WrGLXsVN9MooQ.AWVmAXlGkdyPK6wsnaGeWncVmTmFpaqFkyMI5g.Bn25Ru..AAA.0.0.Bn25Ru.AWXuWffQgGU"
  },
  {
    "domain": "www.facebook.com",
    "expirationDate": null,
    "hostOnly": false,
    "httpOnly": false,
    "name": "ps_n",
    "path": "/",
    "sameSite": "no_restriction",
    "secure": true,
    "session": true,
    "storeId": null,
    "value": "1"
  },
  {
    "domain": "www.facebook.com",
    "expirationDate": null,
    "hostOnly": false,
    "httpOnly": false,
    "name": "wd",
    "path": "/",
    "sameSite": "no_restriction",
    "secure": true,
    "session": true,
    "storeId": null,
    "value": "1366x641"
  },
  {
    "domain": "www.facebook.com",
    "expirationDate": null,
    "hostOnly": false,
    "httpOnly": false,
    "name": "ps_l",
    "path": "/",
    "sameSite": "no_restriction",
    "secure": true,
    "session": true,
    "storeId": null,
    "value": "1"
  },
  {
    "domain": "www.facebook.com",
    "expirationDate": null,
    "hostOnly": false,
    "httpOnly": false,
    "name": "c_user",
    "path": "/",
    "sameSite": "no_restriction",
    "secure": true,
    "session": true,
    "storeId": null,
    "value": "61572830469986"
  },
  {
    "domain": ".facebook.com",
    "expirationDate": 1750246018.0,
    "hostOnly": false,
    "httpOnly": true,
    "name": "fr",
    "path": "/",
    "sameSite": "no_restriction",
    "secure": true,
    "session": false,
    "storeId": null,
    "value": "1q2WcS8hbHm3mbOTX.AWVhtd3BSADeLp4Zp9rAnZTARIaxGaxNLWuccg.Bn25kS..AAA.0.0.Bn25kS.AWUENE4vkjY"
  },
  {
    "domain": "www.facebook.com",
    "expirationDate": null,
    "hostOnly": false,
    "httpOnly": false,
    "name": "sb",
    "path": "/",
    "sameSite": "no_restriction",
    "secure": true,
    "session": true,
    "storeId": null,
    "value": "yVioZ_22baQMpUV8Qv0XZKZn"
  },
  {
    "domain": ".facebook.com",
    "expirationDate": 1774006018.0,
    "hostOnly": false,
    "httpOnly": true,
    "name": "xs",
    "path": "/",
    "sameSite": "no_restriction",
    "secure": true,
    "session": false,
    "storeId": null,
    "value": "50%3AUe0eL0TgvDGnKg%3A2%3A1739086045%3A-1%3A10542%3A%3AAcU0TTjv9cpFUGFxkwl7MbN7W4zgmhmcIPBO6J9JXkg"
  },
  {
    "domain": "www.facebook.com",
    "expirationDate": null,
    "hostOnly": false,
    "httpOnly": false,
    "name": "datr",
    "path": "/",
    "sameSite": "no_restriction",
    "secure": true,
    "session": true,
    "storeId": null,
    "value": "yVioZ81rP2zCiBZE65eBdZtB"
  },
  {
    "domain": ".facebook.com",
    "expirationDate": 1743074816.0,
    "hostOnly": false,
    "httpOnly": false,
    "name": "wd",
    "path": "/",
    "sameSite": "no_restriction",
    "secure": true,
    "session": false,
    "storeId": null,
    "value": "1034x620"
  },
  {
    "domain": ".facebook.com",
    "expirationDate": 1777030005.0,
    "hostOnly": false,
    "httpOnly": true,
    "name": "sb",
    "path": "/",
    "sameSite": "no_restriction",
    "secure": true,
    "session": false,
    "storeId": null,
    "value": "BpnbZ4qgdXw2h20GAtkKdhIV"
  },
  {
    "domain": ".facebook.com",
    "expirationDate": 1777030005.0,
    "hostOnly": false,
    "httpOnly": true,
    "name": "datr",
    "path": "/",
    "sameSite": "no_restriction",
    "secure": true,
    "session": false,
    "storeId": null,
    "value": "BpnbZ7jk3Is5WUx1ntyeZPYd"
  }
]